[
  {
    "Tarih": "2025-09-30",
    "veriler": [
      {
        "isim": "Finansman Bonosu",
        "yatırım miktarı": 92869117046.48457,
        "yatırımın bütüne oranı": 1.027769103597307
      },
      {
        "isim": "Borsa Yatırım Fonları Katılma Payları",
        "yatırım miktarı": 101925212291.8401,
        "yatırımın bütüne oranı": 1.127991601543014
      },
      {
        "isim": "Devlet Tahvili",
        "yatırım miktarı": 479858370792.6162,
        "yatırımın bütüne oranı": 5.310523274990694
      },
      {
        "isim": "Diğer",
        "yatırım miktarı": 162207952347.0283,
        "yatırımın bütüne oranı": 1.795131978013897
      },
      {
        "isim": "Döviz Cinsi Kamu İç Borçlanma Araçları",
        "yatırım miktarı": 52547540851.16389,
        "yatırımın bütüne oranı": 0.5815360442138278
      },
      {
        "isim": "Gayrı Menkul Sertifikası",
        "yatırım miktarı": 46852928658.94341,
        "yatırımın bütüne oranı": 0.5185145936577379
      },
      {
        "isim": "Gayrimenkul Yatırım Fonları Katılma Payları",
        "yatırım miktarı": 24724943720.6758,
        "yatırımın bütüne oranı": 0.2736273806886027
      },
      {
        "isim": "Gayrimenkul Yatırımları",
        "yatırım miktarı": 98201470973.99861,
        "yatırımın bütüne oranı": 1.086781494265364
      },
      {
        "isim": "Girişim Sermayesi Yatırım Fonları Katılma Payları",
        "yatırım miktarı": 44255219608.5821,
        "yatırımın bütüne oranı": 0.489766122831208
      },
      {
        "isim": "Girişim Sermayesi Yatırımları",
        "yatırım miktarı": 220384824052.2853,
        "yatırımın bütüne oranı": 2.438967013644516
      },
      {
        "isim": "Hazine Bonosu",
        "yatırım miktarı": 3291747926.8539,
        "yatırımın bütüne oranı": 0.03642929882016135
      },
      {
        "isim": "Hisse Senedi",
        "yatırım miktarı": 1000107020471.212,
        "yatırımın bütüne oranı": 11.06803993211842
      },
      {
        "isim": "Kamu Dış Borçlanma Araçları",
        "yatırım miktarı": 293829636088.4879,
        "yatırımın bütüne oranı": 3.251770139494608
      },
      {
        "isim": "Kamu Kira Sertifikaları (Döviz)",
        "yatırım miktarı": 45866007579.60889,
        "yatırımın bütüne oranı": 0.5075924806314966
      },
      {
        "isim": "Kamu Kira Sertifikaları (TL)",
        "yatırım miktarı": 73132733146.1803,
        "yatırımın bütüne oranı": 0.8093493938533791
      },
      {
        "isim": "Kamu Yurt Dışı Kira Sertifikaları",
        "yatırım miktarı": 23438610619.4798,
        "yatırımın bütüne oranı": 0.2593917180658816
      },
      {
        "isim": "Katılma Hesabı (Altın)",
        "yatırım miktarı": 1271319811.6994,
        "yatırımın bütüne oranı": 0.01406951271650159
      },
      {
        "isim": "Katılma Hesabı (Döviz)",
        "yatırım miktarı": 216187422490.3639,
        "yatırımın bütüne oranı": 2.392514976864899
      },
      {
        "isim": "Katılma Hesabı (TL)",
        "yatırım miktarı": 333890309775.9451,
        "yatırımın bütüne oranı": 3.695115828510402
      },
      {
        "isim": "Kıymetli Madenler",
        "yatırım miktarı": 248880738532.3482,
        "yatırımın bütüne oranı": 2.754327183018157
      },
      {
        "isim": "Kıymetli Madenler Cinsinden BYF",
        "yatırım miktarı": 90986868277.34221,
        "yatırımın bütüne oranı": 1.006938528356237
      },
      {
        "isim": "Kıymetli Madenler Cinsinden İhraç Edilen Kamu Borçlanma Araçları",
        "yatırım miktarı": 91781356224.32968,
        "yatırımın bütüne oranı": 1.01573101170337
      },
      {
        "isim": "Kıymetli Madenler Cinsinden İhraç Edilen Kamu Kira Sertifikaları",
        "yatırım miktarı": 615323316966.1467,
        "yatırımın bütüne oranı": 6.809694266655648
      },
      {
        "isim": "Mevduat (Döviz)",
        "yatırım miktarı": 334048516956.9598,
        "yatırımın bütüne oranı": 3.696866684529983
      },
      {
        "isim": "Mevduat (TL)",
        "yatırım miktarı": 1062806426344.316,
        "yatırımın bütüne oranı": 11.76192520011369
      },
      {
        "isim": "Özel Sektör Dış Borçlanma Araçları",
        "yatırım miktarı": 1105935328390.736,
        "yatırımın bütüne oranı": 12.23922652917875
      },
      {
        "isim": "Özel Sektör Kira Sertifikaları",
        "yatırım miktarı": 84954610729.37459,
        "yatırımın bütüne oranı": 0.940180405420282
      },
      {
        "isim": "Özel Sektör Tahvili",
        "yatırım miktarı": 109110861658.8205,
        "yatırımın bütüne oranı": 1.207514145134867
      },
      {
        "isim": "Özel Sektör Yurt Dışı Kira Sertifikaları",
        "yatırım miktarı": 14329740728.4609,
        "yatırımın bütüne oranı": 0.1585851707398092
      },
      {
        "isim": "Takasbank Para Piyasası",
        "yatırım miktarı": 87536216060.63286,
        "yatırımın bütüne oranı": 0.9687506587136484
      },
      {
        "isim": "Ters-Repo",
        "yatırım miktarı": 1236377566479.326,
        "yatırımın bütüne oranı": 13.68281193598769
      },
      {
        "isim": "Vadeli İşlemler Nakit Teminatları",
        "yatırım miktarı": 43810454212.84648,
        "yatırımın bütüne oranı": 0.4848439684420638
      },
      {
        "isim": "Varlığa Dayalı Menkul Kıymetler",
        "yatırım miktarı": 7789830966.383199,
        "yatırımın bütüne oranı": 0.08620893407963402
      },
      {
        "isim": "Yabancı Borsa Yatırım Fonları",
        "yatırım miktarı": 46093030503.83659,
        "yatırımın bütüne oranı": 0.5101049105409223
      },
      {
        "isim": "Yabancı Hisse Senedi",
        "yatırım miktarı": 118119256727.6937,
        "yatırımın bütüne oranı": 1.307208752117637
      },
      {
        "isim": "Yabancı Kamu Borçlanma Araçları",
        "yatırım miktarı": 44892157070.9732,
        "yatırımın bütüne oranı": 0.496815017723162
      },
      {
        "isim": "Yabancı Özel Sektör Borçlanma Araçları",
        "yatırım miktarı": 35316703484.49799,
        "yatırımın bütüne oranı": 0.3908448560365459
      },
      {
        "isim": "Yatırım Fonları Katılma Payları",
        "yatırım miktarı": 343054983878.6122,
        "yatırımın bütüne oranı": 3.796539952985979
      }
    ],
    "toplam_para": 9035990352447.086
  }
]