[
  {
    "Tarih": "2025-08-22",
    "veriler": [
      {
        "isim": "Finansman Bonosu",
        "yatırım miktarı": 87965442796.72804,
        "yatırımın bütüne oranı": 1.036036536823729
      },
      {
        "isim": "Borsa Yatırım Fonları Katılma Payları",
        "yatırım miktarı": 93176331687.27339,
        "yatırımın bütüne oranı": 1.097409174853974
      },
      {
        "isim": "Devlet Tahvili",
        "yatırım miktarı": 469439638537.902,
        "yatırımın bütüne oranı": 5.528950936818129
      },
      {
        "isim": "Diğer",
        "yatırım miktarı": 142951968378.7132,
        "yatırımın bütüne oranı": 1.683655052967301
      },
      {
        "isim": "Döviz Cinsi Kamu İç Borçlanma Araçları",
        "yatırım miktarı": 53793895316.0716,
        "yatırımın bütüne oranı": 0.6335719941103286
      },
      {
        "isim": "Gayrı Menkul Sertifikası",
        "yatırım miktarı": 48242251152.7351,
        "yatırımın bütüne oranı": 0.5681860196890782
      },
      {
        "isim": "Gayrimenkul Yatırım Fonları Katılma Payları",
        "yatırım miktarı": 24497326937.76048,
        "yatırımın bütüne oranı": 0.2885238220273023
      },
      {
        "isim": "Gayrimenkul Yatırımları",
        "yatırım miktarı": 97776739147.25923,
        "yatırımın bütüne oranı": 1.151591704507529
      },
      {
        "isim": "Girişim Sermayesi Yatırım Fonları Katılma Payları",
        "yatırım miktarı": 44950382618.05348,
        "yatırımın bütüne oranı": 0.5294151573149574
      },
      {
        "isim": "Girişim Sermayesi Yatırımları",
        "yatırım miktarı": 222524459330.5661,
        "yatırımın bütüne oranı": 2.620841353986656
      },
      {
        "isim": "Hazine Bonosu",
        "yatırım miktarı": 2497924541.4493,
        "yatırımın bütüne oranı": 0.02941997458195475
      },
      {
        "isim": "Hisse Senedi",
        "yatırım miktarı": 973555029537.0765,
        "yatırımın bütüne oranı": 11.46630482540393
      },
      {
        "isim": "Kamu Dış Borçlanma Araçları",
        "yatırım miktarı": 277351716020.4184,
        "yatırımın bütüne oranı": 3.266584038142313
      },
      {
        "isim": "Kamu Kira Sertifikaları (Döviz)",
        "yatırım miktarı": 43424058244.98038,
        "yatırımın bütüne oranı": 0.5114384636580805
      },
      {
        "isim": "Kamu Kira Sertifikaları (TL)",
        "yatırım miktarı": 51492404842.29762,
        "yatırımın bütüne oranı": 0.6064655743144143
      },
      {
        "isim": "Kamu Yurt Dışı Kira Sertifikaları",
        "yatırım miktarı": 23896909273.201,
        "yatırımın bütüne oranı": 0.2814522423471381
      },
      {
        "isim": "Katılma Hesabı (Altın)",
        "yatırım miktarı": 1039353645.9852,
        "yatırımın bütüne oranı": 0.01224126563439155
      },
      {
        "isim": "Katılma Hesabı (Döviz)",
        "yatırım miktarı": 195965703149.1407,
        "yatırımın bütüne oranı": 2.308038497527058
      },
      {
        "isim": "Katılma Hesabı (TL)",
        "yatırım miktarı": 325875311038.5339,
        "yatırımın bütüne oranı": 3.838083660476681
      },
      {
        "isim": "Kıymetli Madenler",
        "yatırım miktarı": 191908404958.6029,
        "yatırımın bütüne oranı": 2.260252582597948
      },
      {
        "isim": "Kıymetli Madenler Cinsinden BYF",
        "yatırım miktarı": 64502071642.87339,
        "yatırımın bütüne oranı": 0.7596904056660334
      },
      {
        "isim": "Kıymetli Madenler Cinsinden İhraç Edilen Kamu Borçlanma Araçları",
        "yatırım miktarı": 78098463024.7171,
        "yatırımın bütüne oranı": 0.9198255427459017
      },
      {
        "isim": "Kıymetli Madenler Cinsinden İhraç Edilen Kamu Kira Sertifikaları",
        "yatırım miktarı": 524977005350.2371,
        "yatırımın bütüne oranı": 6.183057132924276
      },
      {
        "isim": "Mevduat (Döviz)",
        "yatırım miktarı": 265168678306.6146,
        "yatırımın bütüne oranı": 3.123095052016598
      },
      {
        "isim": "Mevduat (TL)",
        "yatırım miktarı": 954514430265.5402,
        "yatırımın bütüne oranı": 11.24204907335916
      },
      {
        "isim": "Özel Sektör Dış Borçlanma Araçları",
        "yatırım miktarı": 1046486258396.233,
        "yatırımın bütüne oranı": 12.32527188532248
      },
      {
        "isim": "Özel Sektör Kira Sertifikaları",
        "yatırım miktarı": 73552614586.5015,
        "yatırımın bütüne oranı": 0.8662855965679733
      },
      {
        "isim": "Özel Sektör Tahvili",
        "yatırım miktarı": 112988688699.0128,
        "yatırımın bütüne oranı": 1.330754510160139
      },
      {
        "isim": "Özel Sektör Yurt Dışı Kira Sertifikaları",
        "yatırım miktarı": 7836003243.767399,
        "yatırımın bütüne oranı": 0.09229062464873139
      },
      {
        "isim": "Takasbank Para Piyasası",
        "yatırım miktarı": 93095380160.9505,
        "yatırımın bütüne oranı": 1.096455746594925
      },
      {
        "isim": "Ters-Repo",
        "yatırım miktarı": 1350239822903.296,
        "yatırımın bütüne oranı": 15.90281075757
      },
      {
        "isim": "Vadeli İşlemler Nakit Teminatları",
        "yatırım miktarı": 40627422965.20136,
        "yatırımın bütüne oranı": 0.4785003434383403
      },
      {
        "isim": "Varlığa Dayalı Menkul Kıymetler",
        "yatırım miktarı": 6812054814.9168,
        "yatırımın bütüne oranı": 0.08023079808065628
      },
      {
        "isim": "Yabancı Borsa Yatırım Fonları",
        "yatırım miktarı": 36826430841.13387,
        "yatırımın bütüne oranı": 0.4337331417792402
      },
      {
        "isim": "Yabancı Hisse Senedi",
        "yatırım miktarı": 104066847298.9397,
        "yatırımın bütüne oranı": 1.225675136120245
      },
      {
        "isim": "Yabancı Kamu Borçlanma Araçları",
        "yatırım miktarı": 39217430951.96459,
        "yatırımın bütüne oranı": 0.4618937852730095
      },
      {
        "isim": "Yabancı Özel Sektör Borçlanma Araçları",
        "yatırım miktarı": 31071230739.1719,
        "yatırımın bütüne oranı": 0.3659497328314479
      },
      {
        "isim": "Yatırım Fonları Katılma Payları",
        "yatırım miktarı": 288167332693.2449,
        "yatırımın bütüne oranı": 3.393967857117927
      }
    ],
    "toplam_para": 8490573418039.067
  }
]