[
  {
    "Tarih": "2025-07-27",
    "veriler": [
      {
        "isim": "Finansman Bonosu",
        "yatırım miktarı": 87376870148.91557,
        "yatırımın bütüne oranı": 1.070929113724986
      },
      {
        "isim": "Borsa Yatırım Fonları Katılma Payları",
        "yatırım miktarı": 94324251264.7742,
        "yatırımın bütüne oranı": 1.156079253440863
      },
      {
        "isim": "Devlet Tahvili",
        "yatırım miktarı": 440697852874.1454,
        "yatırımın bütüne oranı": 5.401385517639421
      },
      {
        "isim": "Diğer",
        "yatırım miktarı": 121786728494.8929,
        "yatırımın bütüne oranı": 1.492671378457698
      },
      {
        "isim": "Döviz Cinsi Kamu İç Borçlanma Araçları",
        "yatırım miktarı": 50285654299.47501,
        "yatırımın bütüne oranı": 0.6163229593854496
      },
      {
        "isim": "Gayrı Menkul Sertifikası",
        "yatırım miktarı": 45654029734.13,
        "yatırımın bütüne oranı": 0.5595557441897315
      },
      {
        "isim": "Gayrimenkul Yatırım Fonları Katılma Payları",
        "yatırım miktarı": 24216161757.46091,
        "yatırımın bütüne oranı": 0.2968038635915865
      },
      {
        "isim": "Gayrimenkul Yatırımları",
        "yatırım miktarı": 96551026442.7279,
        "yatırımın bütüne oranı": 1.183371583364405
      },
      {
        "isim": "Girişim Sermayesi Yatırım Fonları Katılma Payları",
        "yatırım miktarı": 45182623509.26691,
        "yatırımın bütüne oranı": 0.5537779834421027
      },
      {
        "isim": "Girişim Sermayesi Yatırımları",
        "yatırım miktarı": 223144264430.7489,
        "yatırımın bütüne oranı": 2.734953643136434
      },
      {
        "isim": "Hazine Bonosu",
        "yatırım miktarı": 2163383229.6425,
        "yatırımın bütüne oranı": 0.02651537049587595
      },
      {
        "isim": "Hisse Senedi",
        "yatırım miktarı": 923719944334.7235,
        "yatırımın bütüne oranı": 11.3215154036821
      },
      {
        "isim": "Kamu Dış Borçlanma Araçları",
        "yatırım miktarı": 267913918130.4426,
        "yatırımın bütüne oranı": 3.283670088079759
      },
      {
        "isim": "Kamu Kira Sertifikaları (Döviz)",
        "yatırım miktarı": 41495937379.97761,
        "yatırımın bütüne oranı": 0.5085923467593839
      },
      {
        "isim": "Kamu Kira Sertifikaları (TL)",
        "yatırım miktarı": 49119456091.7404,
        "yatırımın bütüne oranı": 0.6020295243962085
      },
      {
        "isim": "Kamu Yurt Dışı Kira Sertifikaları",
        "yatırım miktarı": 22342691303.4054,
        "yatırımın bütüne oranı": 0.2738417907966672
      },
      {
        "isim": "Katılma Hesabı (Altın)",
        "yatırım miktarı": 1022506117.9622,
        "yatırımın bütüne oranı": 0.01253228192794481
      },
      {
        "isim": "Katılma Hesabı (Döviz)",
        "yatırım miktarı": 188376705420.5699,
        "yatırımın bütüne oranı": 2.308827242709236
      },
      {
        "isim": "Katılma Hesabı (TL)",
        "yatırım miktarı": 318067662787.6766,
        "yatırımın bütüne oranı": 3.898376305231067
      },
      {
        "isim": "Kıymetli Madenler",
        "yatırım miktarı": 187151293096.1987,
        "yatırımın bütüne oranı": 2.293808053623497
      },
      {
        "isim": "Kıymetli Madenler Cinsinden BYF",
        "yatırım miktarı": 59544354896.34692,
        "yatırımın bütüne oranı": 0.7298016409582079
      },
      {
        "isim": "Kıymetli Madenler Cinsinden İhraç Edilen Kamu Borçlanma Araçları",
        "yatırım miktarı": 78495576957.4457,
        "yatırımın bütüne oranı": 0.962076102280851
      },
      {
        "isim": "Kıymetli Madenler Cinsinden İhraç Edilen Kamu Kira Sertifikaları",
        "yatırım miktarı": 526666579521.711,
        "yatırımın bütüne oranı": 6.455055809100251
      },
      {
        "isim": "Mevduat (Döviz)",
        "yatırım miktarı": 251577897156.8331,
        "yatırımın bütüne oranı": 3.083448674412227
      },
      {
        "isim": "Mevduat (TL)",
        "yatırım miktarı": 936371450712.1609,
        "yatırımın bütüne oranı": 11.476577795926
      },
      {
        "isim": "Özel Sektör Dış Borçlanma Araçları",
        "yatırım miktarı": 959372530904.1299,
        "yatırımın bütüne oranı": 11.75848908872834
      },
      {
        "isim": "Özel Sektör Kira Sertifikaları",
        "yatırım miktarı": 71930488490.99829,
        "yatırımın bütüne oranı": 0.8816115083795565
      },
      {
        "isim": "Özel Sektör Tahvili",
        "yatırım miktarı": 110203893470.9216,
        "yatırımın bütüne oranı": 1.350707089447304
      },
      {
        "isim": "Özel Sektör Yurt Dışı Kira Sertifikaları",
        "yatırım miktarı": 7507259650.240801,
        "yatırımın bütüne oranı": 0.09201225576097737
      },
      {
        "isim": "Takasbank Para Piyasası",
        "yatırım miktarı": 96171198377.36435,
        "yatırımın bütüne oranı": 1.178716244569202
      },
      {
        "isim": "Ters-Repo",
        "yatırım miktarı": 1280625291504.512,
        "yatırımın bütüne oranı": 15.69590334498552
      },
      {
        "isim": "Vadeli İşlemler Nakit Teminatları",
        "yatırım miktarı": 38156559103.78453,
        "yatırımın bütüne oranı": 0.467663466935456
      },
      {
        "isim": "Varlığa Dayalı Menkul Kıymetler",
        "yatırım miktarı": 5923476931.924798,
        "yatırımın bütüne oranı": 0.07260072248027703
      },
      {
        "isim": "Yabancı Borsa Yatırım Fonları",
        "yatırım miktarı": 37413876626.64429,
        "yatırımın bütüne oranı": 0.4585608258627401
      },
      {
        "isim": "Yabancı Hisse Senedi",
        "yatırım miktarı": 99966069329.31897,
        "yatırımın bütüne oranı": 1.225227841727022
      },
      {
        "isim": "Yabancı Kamu Borçlanma Araçları",
        "yatırım miktarı": 39397390774.6554,
        "yatırımın bütüne oranı": 0.4828716422718224
      },
      {
        "isim": "Yabancı Özel Sektör Borçlanma Araçları",
        "yatırım miktarı": 31033699153.41159,
        "yatırımın bütüne oranı": 0.3803625819204671
      },
      {
        "isim": "Yatırım Fonları Katılma Payları",
        "yatırım miktarı": 298027386247.6299,
        "yatırımın bütüne oranı": 3.652753916179378
      }
    ],
    "toplam_para": 8158977940658.91
  }
]